topsis_Akhil_102203565/__init__.py
topsis_Akhil_102203565/main.py
topsis_Akhil_102203565-3.0.0.dist-info/LICENSE
topsis_Akhil_102203565-3.0.0.dist-info/METADATA
topsis_Akhil_102203565-3.0.0.dist-info/WHEEL
topsis_Akhil_102203565-3.0.0.dist-info/entry_points.txt
topsis_Akhil_102203565-3.0.0.dist-info/top_level.txt
topsis_Akhil_102203565-3.0.0.dist-info/RECORD
