Metadata-Version: 2.2
Name: topsis_Akhil_102203565
Version: 3.0.0
Summary: A Python package for TOPSIS (Technique for Order Preference by Similarity to Ideal Solution) algorithm
Home-page: https://github.com/YOUR_GITHUB_USERNAME/topsis_Akhil_102203565
Author: Akhil Goyal
Author-email: goyalakhil06022004@gmail.com
Classifier: Programming Language :: Python :: 3
Classifier: License :: OSI Approved :: MIT License
Classifier: Operating System :: OS Independent
Requires-Python: >=3.6
License-File: LICENSE
Requires-Dist: numpy
Requires-Dist: pandas
Requires-Dist: openpyxl
Dynamic: author
Dynamic: author-email
Dynamic: classifier
Dynamic: description-content-type
Dynamic: home-page
Dynamic: requires-dist
Dynamic: requires-python
Dynamic: summary
